mlgenotype/__init__.py
mlgenotype/__main__.py
mlgenotype/figure1calcs.py
mlgenotype/rfgenotype.py
mlgenotype/rfmodelpredict.py
mlgenotype/rfmodeltrain.py
mlgenotype/rftrainpredict.py
mlgenotype/__pycache__/__init__.cpython-310.pyc
mlgenotype/__pycache__/rfgenotype.cpython-310.pyc
mlgenotype/__pycache__/rfmodelpredict.cpython-310.pyc
mlgenotype/__pycache__/rfmodeltrain.cpython-310.pyc
mlgenotype-0.1.12.dist-info/LICENSE.md
mlgenotype-0.1.12.dist-info/METADATA
mlgenotype-0.1.12.dist-info/WHEEL
mlgenotype-0.1.12.dist-info/entry_points.txt
mlgenotype-0.1.12.dist-info/top_level.txt
mlgenotype-0.1.12.dist-info/RECORD
