Metadata-Version: 2.1
Name: mlgenotype
Version: 0.1.12
Summary: A package with utilities for training classifiers to recognize SVs in short read datasets
Home-page: https://github.com/nhansen/mlgenotype
Author: Nancy F Hansen, Gracelyn Hill, Jennifer Lin
Author-email: "Nancy F. Hansen" <nhansen@mail.nih.gov>
Project-URL: Homepage, https://github.com/nhansen/mlgenotype
Project-URL: Bug Tracker, https://github.com/nhansen/mlgenotype/issues
Classifier: Programming Language :: Python :: 3
Classifier: License :: OSI Approved :: MIT License
Classifier: Operating System :: OS Independent
Requires-Python: >=3.7
License-File: LICENSE.md
Requires-Dist: pandas (>=1.0)
Requires-Dist: scikit-learn (==1.0.2)
